odoo/addons/account_payment_batch_oca_tier_validation/README.rst
odoo/addons/account_payment_batch_oca_tier_validation/__init__.py
odoo/addons/account_payment_batch_oca_tier_validation/__manifest__.py
odoo/addons/account_payment_batch_oca_tier_validation/i18n/account_payment_batch_oca_tier_validation.pot
odoo/addons/account_payment_batch_oca_tier_validation/i18n/account_payment_order_tier_validation.pot
odoo/addons/account_payment_batch_oca_tier_validation/i18n/fr.po
odoo/addons/account_payment_batch_oca_tier_validation/i18n/it.po
odoo/addons/account_payment_batch_oca_tier_validation/i18n/pt_BR.po
odoo/addons/account_payment_batch_oca_tier_validation/models/__init__.py
odoo/addons/account_payment_batch_oca_tier_validation/models/account_payment_order.py
odoo/addons/account_payment_batch_oca_tier_validation/models/tier_definition.py
odoo/addons/account_payment_batch_oca_tier_validation/readme/CONFIGURE.md
odoo/addons/account_payment_batch_oca_tier_validation/readme/CONTRIBUTORS.md
odoo/addons/account_payment_batch_oca_tier_validation/readme/DESCRIPTION.md
odoo/addons/account_payment_batch_oca_tier_validation/readme/INSTALL.md
odoo/addons/account_payment_batch_oca_tier_validation/readme/USAGE.md
odoo/addons/account_payment_batch_oca_tier_validation/static/description/icon.png
odoo/addons/account_payment_batch_oca_tier_validation/static/description/index.html
odoo/addons/account_payment_batch_oca_tier_validation/tests/__init__.py
odoo/addons/account_payment_batch_oca_tier_validation/tests/test_payment_order_tier_validation.py
odoo/addons/account_payment_batch_oca_tier_validation/views/account_payment_order.xml
odoo_addon_account_payment_batch_oca_tier_validation-18.0.1.0.0.3.dist-info/METADATA
odoo_addon_account_payment_batch_oca_tier_validation-18.0.1.0.0.3.dist-info/WHEEL
odoo_addon_account_payment_batch_oca_tier_validation-18.0.1.0.0.3.dist-info/top_level.txt
odoo_addon_account_payment_batch_oca_tier_validation-18.0.1.0.0.3.dist-info/RECORD
